wildboottest/__init__.py
wildboottest/weights.py
wildboottest/wildboottest.py
wildboottest-0.3.2.dist-info/LICENSE
wildboottest-0.3.2.dist-info/METADATA
wildboottest-0.3.2.dist-info/WHEEL
wildboottest-0.3.2.dist-info/RECORD
