Metadata-Version: 2.1
Name: wildboottest
Version: 0.3.2
Summary: Wild Cluster Bootstrap Inference for Linear Models in Python
Home-page: https://github.com/s3alfisc/wildboottest
License: MIT
Author: Alexander Fischer
Author-email: alexander-fischer1801@t-online.de
Maintainer: Aleksandr Michuda
Maintainer-email: amichuda@gmail.com
Requires-Python: >=3.8,<4.0
Classifier: License :: OSI Approved :: MIT License
Classifier: Operating System :: OS Independent
Classifier: Programming Language :: Python :: 3
Classifier: Programming Language :: Python :: 3.8
Classifier: Programming Language :: Python :: 3.9
Classifier: Programming Language :: Python :: 3.10
Classifier: Programming Language :: Python :: 3.11
Classifier: Programming Language :: Python :: 3.12
Requires-Dist: numba (>=0.57)
Requires-Dist: numpy (>=1.18)
Requires-Dist: pandas (>=1.4)
Requires-Dist: statsmodels (>=0.13)
Requires-Dist: tabulate (>=0.9.0)
Project-URL: Repository, https://github.com/s3alfisc/wildboottest
